mlflowrate/__init__.py
mlflowrate/workflow.py
mlflowrate-0.0.1.dist-info/METADATA
mlflowrate-0.0.1.dist-info/RECORD
mlflowrate-0.0.1.dist-info/WHEEL
mlflowrate-0.0.1.dist-info/top_level.txt
