Metadata-Version: 2.1
Name: mlflowrate
Version: 0.0.1
Summary: A data exploration package for oil well flow rate prediction.
Home-page: https://github.com/kkf18/acse-9-independent-research-project-kkf18
Author: Kevin Fung
Author-email: kkf18@imperial.ac.uk
License: MIT
Platform: UNKNOWN
